tinyscibio/__init__.py
tinyscibio/_intervals.py
tinyscibio/_io.py
tinyscibio/_version.py
tinyscibio/api_server.py
tinyscibio/bam.py
tinyscibio/py.typed
tinyscibio-0.4.3.dist-info/METADATA
tinyscibio-0.4.3.dist-info/WHEEL
tinyscibio-0.4.3.dist-info/RECORD
