Metadata-Version: 2.3
Name: tinyscibio
Version: 0.4.3
Summary: tinyscibio provides convenient shortcut functions to boost daily bioinformatics work.
Project-URL: Source, https://github.com/svm-zhang/tinyscibio
Project-URL: Documentation, https://svm-zhang.github.io/tinyscibio/
Project-URL: Issues, https://github.com/svm-zhang/tinyscibio/issues
Author-email: Simo Zhang <svm.zhang@gmail.com>
Maintainer-email: Simo Zhang <svm.zhang@gmail.com>
License: MIT
Keywords: bioinformatics,genomics,sequencing
Classifier: Development Status :: 4 - Beta
Classifier: Intended Audience :: Developers
Classifier: License :: OSI Approved :: MIT License
Classifier: Operating System :: POSIX
Classifier: Programming Language :: Python :: 3 :: Only
Classifier: Programming Language :: Python :: 3.10
Classifier: Programming Language :: Python :: 3.11
Classifier: Programming Language :: Python :: 3.12
Classifier: Programming Language :: Python :: 3.13
Classifier: Topic :: Scientific/Engineering :: Bio-Informatics
Classifier: Topic :: Software Development :: Libraries
Requires-Python: >=3.10
Requires-Dist: ncls>=0.0.68
Requires-Dist: numpy>=2.1.2
Requires-Dist: polars>=1.12.0
Requires-Dist: pysam>=0.23.0
Requires-Dist: requests>=2.32.3
Requires-Dist: setuptools>=75.3.0
